{
  "pass": 1,
  "totalClaims": 27,
  "deduplicatedClaims": 27,
  "summary": {
    "verified": 0,
    "single_source": 25,
    "inferred": 2
  },
  "note": "All claims are single-source (GitHub source code via gh API). Verified requires 2+ distinct hostnames -- not possible from a single repo. Inferred claims are derived from comparing two sources (OpenClaw source + WorkTrain source).",
  "claims": [
    { "id": "SQ1-C1", "confidence": "single-source", "subQuestion": "SQ1" },
    { "id": "SQ1-C2", "confidence": "single-source", "subQuestion": "SQ1" },
    { "id": "SQ1-C3", "confidence": "single-source", "subQuestion": "SQ1" },
    { "id": "SQ1-C4", "confidence": "single-source", "subQuestion": "SQ1" },
    { "id": "SQ1-C5", "confidence": "single-source", "subQuestion": "SQ1" },
    { "id": "SQ1-C6", "confidence": "single-source", "subQuestion": "SQ1" },
    { "id": "SQ3-C1", "confidence": "inferred", "subQuestion": "SQ3", "derivation": "OpenClaw registry.ts + WorkTrain buildAgentReadySession() -- both read to derive the minimal seam" },
    { "id": "SQ3-C2", "confidence": "single-source", "subQuestion": "SQ3" },
    { "id": "SQ3-C3", "confidence": "single-source", "subQuestion": "SQ3" },
    { "id": "SQ3-C4", "confidence": "single-source", "subQuestion": "SQ3" },
    { "id": "SQ3-C5", "confidence": "single-source", "subQuestion": "SQ3" },
    { "id": "SQ4-C1", "confidence": "single-source", "subQuestion": "SQ4" },
    { "id": "SQ4-C2", "confidence": "single-source", "subQuestion": "SQ4" },
    { "id": "SQ4-C3", "confidence": "single-source", "subQuestion": "SQ4" },
    { "id": "SQ4-C4", "confidence": "single-source", "subQuestion": "SQ4" },
    { "id": "SQ5-C1", "confidence": "single-source", "subQuestion": "SQ5" },
    { "id": "SQ5-C2", "confidence": "single-source", "subQuestion": "SQ5" },
    { "id": "SQ5-C3", "confidence": "single-source", "subQuestion": "SQ5" },
    { "id": "SQ5-C4", "confidence": "single-source", "subQuestion": "SQ5" },
    { "id": "SQ6-C1", "confidence": "single-source", "subQuestion": "SQ6" },
    { "id": "SQ6-C2", "confidence": "inferred", "subQuestion": "SQ6", "derivation": "WorkTrain daemon-events.ts + OpenClaw session-lifecycle-events.ts both read -- comparison yields the inference about storage split vs schema quality" },
    { "id": "SQ6-C3", "confidence": "single-source", "subQuestion": "SQ6" },
    { "id": "SQ2-C1", "confidence": "single-source", "subQuestion": "SQ2" },
    { "id": "SQ2-C2", "confidence": "single-source", "subQuestion": "SQ2" },
    { "id": "SQ2-C3", "confidence": "single-source", "subQuestion": "SQ2" },
    { "id": "SQ7-C1", "confidence": "single-source", "subQuestion": "SQ7" },
    { "id": "SQ7-C2", "confidence": "single-source", "subQuestion": "SQ7" },
    { "id": "SQ7-C3", "confidence": "single-source", "subQuestion": "SQ7" },
    { "id": "SQ7-C4", "confidence": "single-source", "subQuestion": "SQ7" },
    { "id": "SQ7-C5", "confidence": "single-source", "subQuestion": "SQ7" },
    { "id": "SQ7-C6", "confidence": "single-source", "subQuestion": "SQ7" },
    { "id": "SQ7-C7", "confidence": "single-source", "subQuestion": "SQ7" }
  ]
}
